tm4jReporter/__init__.py
tm4jReporter/cmder.py
tm4jReporter/tm4jApi.py
tm4jReporter/tm4jParse.py
tm4jReporter/tm4jReporter.py
tm4jReporter-0.3.0.dist-info/METADATA
tm4jReporter-0.3.0.dist-info/WHEEL
tm4jReporter-0.3.0.dist-info/entry_points.txt
tm4jReporter-0.3.0.dist-info/top_level.txt
tm4jReporter-0.3.0.dist-info/RECORD
