Metadata-Version: 2.1
Name: tm4jReporter
Version: 0.3.0
Summary: TM4J (Zephyr Scale) 
Home-page: https://github.com/seoktaehyeon/tm4j-reporter
Author: Will
Author-email: v.stone@163.com
Maintainer: Will
Maintainer-email: v.stone@163.com
License: MIT
Platform: any
Requires-Dist: requests
